hw2_fedaniil/__about__.py
hw2_fedaniil/__init__.py
hw2_fedaniil/article.py
hw2_fedaniil/image.py
hw2_fedaniil/pdf.py
hw2_fedaniil/preamble.py
hw2_fedaniil/table.py
hw2_fedaniil-0.1.1.dist-info/METADATA
hw2_fedaniil-0.1.1.dist-info/WHEEL
hw2_fedaniil-0.1.1.dist-info/licenses/LICENSE.txt
hw2_fedaniil-0.1.1.dist-info/RECORD
